hakowan/__init__.py
hakowan/__main__.py
hakowan/py.typed
hakowan/common/__init__.py
hakowan/common/color.py
hakowan/common/default.py
hakowan/common/envmaps.py
hakowan/common/exception.py
hakowan/common/logger.py
hakowan/common/named_colors.py
hakowan/common/to_color.py
hakowan/common/colormap/__init__.py
hakowan/common/colormap/colorbrewer2.py
hakowan/common/colormap/colormap.py
hakowan/common/colormap/coolwarm.py
hakowan/common/colormap/inferno.py
hakowan/common/colormap/magma.py
hakowan/common/colormap/named_colormaps.py
hakowan/common/colormap/plasma.py
hakowan/common/colormap/turbo.py
hakowan/common/colormap/viridis.py
hakowan/compiler/__init__.py
hakowan/compiler/attribute.py
hakowan/compiler/channel.py
hakowan/compiler/color.py
hakowan/compiler/compile.py
hakowan/compiler/scene.py
hakowan/compiler/texture.py
hakowan/compiler/transform.py
hakowan/compiler/utils.py
hakowan/compiler/view.py
hakowan/envmaps/README.md
hakowan/envmaps/museum.exr
hakowan/grammar/__init__.py
hakowan/grammar/channel/__init__.py
hakowan/grammar/channel/channel.py
hakowan/grammar/channel/curvestyle.py
hakowan/grammar/channel/material/__init__.py
hakowan/grammar/channel/material/material.py
hakowan/grammar/channel/material/medium.py
hakowan/grammar/dataframe/__init__.py
hakowan/grammar/dataframe/dataframe.py
hakowan/grammar/layer/__init__.py
hakowan/grammar/layer/layer.py
hakowan/grammar/layer/layer_spec.py
hakowan/grammar/mark/__init__.py
hakowan/grammar/mark/mark.py
hakowan/grammar/scale/__init__.py
hakowan/grammar/scale/attribute.py
hakowan/grammar/scale/offset.py
hakowan/grammar/scale/scale.py
hakowan/grammar/texture/__init__.py
hakowan/grammar/texture/texture.py
hakowan/grammar/transform/__init__.py
hakowan/grammar/transform/transform.py
hakowan/render/__init__.py
hakowan/render/base_shapes.py
hakowan/render/bsdf.py
hakowan/render/color.py
hakowan/render/emitter.py
hakowan/render/film.py
hakowan/render/integrator.py
hakowan/render/medium.py
hakowan/render/render.py
hakowan-0.3.9.dist-info/licenses/LICENSE
hakowan-0.3.9.dist-info/WHEEL
hakowan-0.3.9.dist-info/METADATA
hakowan-0.3.9.dist-info/RECORD
