Metadata-Version: 2.4
Name: hakowan
Version: 0.3.9
Summary: Hakowan: A 3D data visualization grammar 
Author-email: Qingnan Zhou <qnzhou@gmail.com>, Zhicheng Liu <leozcliu@umd.edu>
Requires-Python: >=3.10
Classifier: License :: OSI Approved :: Apache Software License
License-File: LICENSE
Requires-Dist: lagrange-open>=6.39
Requires-Dist: mitsuba~=3.7
Requires-Dist: numpy>=1.22
Requires-Dist: Pillow~=11.0
